[
  {
    "id": 0,
    "requestUser": "john190",
    "game": "Rocket League",
    "description": "Looking for players to join me in a match today from 3pm to 4pm!",
    "votes": ["gamernerd", "anon65"]
  },
  {
    "id": 1,
    "requestUser": "anon65",
    "game": "Call of Duty",
    "description": "Is anyone available for a game on May 15th from 12pm to 3pm?",
    "votes": []
  },
  {
    "id": 2,
    "requestUser": "gamernerd",
    "game": "Minecraft",
    "description": "Looking for players to join me in a match today from 3pm to 4pm!",
    "votes": ["john190", "anon65"]
  }
]
